nonebot_plugin_group_relay/__init__.py
nonebot_plugin_group_relay/config.py
nonebot_plugin_group_relay-0.1.1.dist-info/METADATA
nonebot_plugin_group_relay-0.1.1.dist-info/WHEEL
nonebot_plugin_group_relay-0.1.1.dist-info/entry_points.txt
nonebot_plugin_group_relay-0.1.1.dist-info/licenses/LICENSE
nonebot_plugin_group_relay-0.1.1.dist-info/RECORD
