Metadata-Version: 2.4
Name: nonebot-plugin-group-relay
Version: 0.1.1
Summary: 在多个 QQ 群之间中继/转发消息的 NoneBot2 插件
License: MIT License
License-File: LICENSE
Keywords: nonebot,nonebot2,nonebot-plugin,qqbot,onebot,group,relay,forward
Author: TonyLiang
Author-email: tghrtwld@example.com
Requires-Python: >=3.9, <4.0
Classifier: Programming Language :: Python :: 3
Classifier: Programming Language :: Python :: 3 :: Only
Classifier: Programming Language :: Python :: 3.9
Classifier: License :: OSI Approved :: MIT License
Classifier: Framework :: AsyncIO
Classifier: Intended Audience :: Developers
Classifier: Topic :: Communications :: Chat
Provides-Extra: dev
Requires-Dist: nonebot-adapter-onebot (>=2.4.6)
Requires-Dist: nonebot2[aiohttp,fastapi,httpx,websockets] (>=2.4.4)
Requires-Dist: pyright[nodejs] ; extra == "dev"
Requires-Dist: ruff ; extra == "dev"
Project-URL: Homepage, https://github.com/TonyLiangP2010405/nonebot-plugin-group-relay
Project-URL: Issues, https://github.com/TonyLiangP2010405/nonebot-plugin-group-relay/issues
Project-URL: Repository, https://github.com/TonyLiangP2010405/nonebot-plugin-group-relay
